README.rst
setup.cfg
setup.py
octopy/__init__.py
octopy/error.py
octopy/model.py
octopy/oauth2.py
octopy/request.py
octopy.egg-info/PKG-INFO
octopy.egg-info/SOURCES.txt
octopy.egg-info/dependency_links.txt
octopy.egg-info/requires.txt
octopy.egg-info/top_level.txt
octopy.egg-info/zip-safe
octopy/modules/__init__.py
octopy/modules/activity/__init__.py
octopy/modules/activity/event.py
octopy/modules/activity/feed.py
octopy/modules/activity/notification.py
octopy/modules/activity/starring.py
octopy/modules/activity/watch.py
octopy/modules/apps/__init__.py
octopy/modules/apps/installation.py
octopy/modules/apps/oauth.py
octopy/modules/check/__init__.py
octopy/modules/check/run.py
octopy/modules/check/suite.py
octopy/modules/data/__init__.py
octopy/modules/data/blob.py
octopy/modules/data/commit.py
octopy/modules/data/reference.py
octopy/modules/data/tag.py
octopy/modules/data/tree.py
octopy/modules/gist/__init__.py
octopy/modules/gist/comment.py
octopy/modules/interaction/__init__.py
octopy/modules/interaction/organization.py
octopy/modules/interaction/repository.py
octopy/modules/issue/__init__.py
octopy/modules/issue/assignee.py
octopy/modules/issue/comment.py
octopy/modules/issue/event.py
octopy/modules/issue/label.py
octopy/modules/issue/milestone.py
octopy/modules/issue/timeline.py
octopy/modules/marketplace/__init__.py
octopy/modules/migration/__init__.py
octopy/modules/migration/organization.py
octopy/modules/migration/source_import.py
octopy/modules/migration/user.py
octopy/modules/miscellaneous/__init__.py
octopy/modules/miscellaneous/code_of_conduct.py
octopy/modules/miscellaneous/emoji.py
octopy/modules/miscellaneous/gitignore.py
octopy/modules/miscellaneous/license.py
octopy/modules/miscellaneous/markdown.py
octopy/modules/miscellaneous/meta.py
octopy/modules/miscellaneous/rate_limit.py
octopy/modules/organization/__init__.py
octopy/modules/organization/blocking_user.py
octopy/modules/organization/member.py
octopy/modules/organization/outside_collaborator.py
octopy/modules/organization/webhook.py
octopy/modules/project/__init__.py
octopy/modules/project/card.py
octopy/modules/project/collaborator.py
