Metadata-Version: 1.1
Name: octopy
Version: 0.0.2
Summary: Github API Wrapper
Home-page: https://github.com/monzita/octopy
Author: Monika Ilieva
Author-email: hidden@hidden.com
License: MIT License
Keywords: octopy github wrapper api python3
Platform: UNKNOWN
Classifier: Development Status :: 3 - Alpha
Classifier: Programming Language :: Python :: 3.8
Classifier: Programming Language :: Python :: 3.9
Classifier: Programming Language :: Python :: 3 :: Only
